README.md
setup.py
auto_diff_pkg/AutoDiff.py
auto_diff_pkg/ReverseAutoDiff.py
auto_diff_pkg/__init__.py
auto_diff_pkg.egg-info/PKG-INFO
auto_diff_pkg.egg-info/SOURCES.txt
auto_diff_pkg.egg-info/dependency_links.txt
auto_diff_pkg.egg-info/requires.txt
auto_diff_pkg.egg-info/top_level.txt
docs/__init__.py