Metadata-Version: 2.1
Name: auto-diff-pkg
Version: 0.1.1
Summary: A package for performing automatic differentiation
Home-page: https://github.com/DeriveMeCrazy-AutoDiff/cs107-FinalProject/tree/master
Author: DeriveMeCrazy-AutoDiff Group 21
Author-email: jalling@g.harvard.edu, mod821@g.harvard.edu, tliu@g.harvard.edu, alk264@g.harvard.edu
License: UNKNOWN
Platform: UNKNOWN
Classifier: Programming Language :: Python :: 3
Classifier: License :: OSI Approved :: MIT License
Classifier: Operating System :: OS Independent
Requires-Python: >=3.7
